manaba/__init__.py
manaba/test_manaba.py
manaba/models/ManabaAnswerViewType.py
manaba/models/ManabaContent.py
manaba/models/ManabaContentPage.py
manaba/models/ManabaCourse.py
manaba/models/ManabaCourseLamps.py
manaba/models/ManabaCourseNews.py
manaba/models/ManabaDrillDetails.py
manaba/models/ManabaFile.py
manaba/models/ManabaGradePosition.py
manaba/models/ManabaModel.py
manaba/models/ManabaPortfolioType.py
manaba/models/ManabaQuery.py
manaba/models/ManabaQueryDetails.py
manaba/models/ManabaReport.py
manaba/models/ManabaReportDetails.py
manaba/models/ManabaResultViewType.py
manaba/models/ManabaStudentReSubmitType.py
manaba/models/ManabaSurvey.py
manaba/models/ManabaSurveyDetails.py
manaba/models/ManabaTaskStatus.py
manaba/models/ManabaTaskStatusFlag.py
manaba/models/ManabaTaskYourStatusFlag.py
manaba/models/ManabaThread.py
manaba/models/ManabaThreadComment.py
manaba/models/__init__.py
get_manaba-2.3.3.dist-info/LICENSE
get_manaba-2.3.3.dist-info/METADATA
get_manaba-2.3.3.dist-info/WHEEL
get_manaba-2.3.3.dist-info/top_level.txt
get_manaba-2.3.3.dist-info/RECORD
