Metadata-Version: 2.1
Name: get-manaba
Version: 2.3.3
Summary: Library for get various information about manaba.
Home-page: https://github.com/book000/get-manaba
Author: Tomachi
Author-email: tomachi@tomacheese.com
Maintainer: Tomachi
Maintainer-email: tomachi@tomacheese.com
License: MIT
Platform: UNKNOWN
Classifier: Programming Language :: Python :: 3.9
Classifier: License :: OSI Approved :: MIT License
License-File: LICENSE
Requires-Dist: beautifulsoup4
Requires-Dist: requests
Requires-Dist: html5lib
